{"result": true, "message": null, "sysData": null, "data": {"commonState": {"hash": "A3ENB88Cid5lrmGbYxlyrw==", "hasChanges": false, "isEmpty": false, "app": {"version": "0.4.3.6"}}, "cards": [{"id": 962020, "name": "КоммерчПрогр-090302-440304 ЛР.doc", "created": "2022-03-18T17:33:40.487", "modified": "2022-03-18T17:34:04.783", "downloadLink": "/AppxIndex/Download?rupRowId=3020372&rpId=741610&fileId=962020", "length": 92.0, "type": 0}, {"id": 962021, "name": "+ФОС-КИТ_B090302ВИАС.docx", "created": "2022-03-15T23:33:23.917", "modified": "2022-03-15T23:33:28.307", "downloadLink": "/AppxIndex/Download?rupRowId=3020372&rpId=741610&fileId=962021", "length": 70.02, "type": 0}]}}