{"result": true, "message": null, "sysData": null, "data": {"commonState": {"app": {"version": "0.4.3.6"}}, "rup": {"items": [{"rupRowId": 3020590, "rupId": 45917, "hasDraft": false, "isDraftCurrupted": false, "index": "Б1.О.22.04", "rupName": "B090302ВИАС_09_4-23.plx", "fgosTypeName": "ФГОС 3++", "studyForm": "очная", "studyLevel": "Бакалавриат", "specName": "09.03.02 Информационные системы и технологии\r\n", "subSpecName": "Информационные системы и технологии", "nagrRows": [], "rpCount": 1, "url": "https://mmis.ru/programs/webplany"}, {"rupRowId": 3021975, "rupId": 45926, "hasDraft": false, "isDraftCurrupted": false, "index": "Б1.О.22.04", "rupName": "B090302ВИС_09_4-23.plx", "fgosTypeName": "ФГОС 3++", "studyForm": "очная", "studyLevel": "Бакалавриат", "specName": "09.03.02 Информационные системы и технологии\r\n", "subSpecName": "Информационные системы и технологии", "nagrRows": [], "rpCount": 1, "url": "https://mmis.ru/programs/webplany"}], "current": 3020590}, "settings": {"allowCreate": true}}}